arcade_clickup/__init__.py
arcade_clickup/constants.py
arcade_clickup/client/__init__.py
arcade_clickup/client/api_client.py
arcade_clickup/debug_tools/README.md
arcade_clickup/debug_tools/http_log_viewer.html
arcade_clickup/debug_tools/http_logging.py
arcade_clickup/models/__init__.py
arcade_clickup/models/api_models.py
arcade_clickup/models/tool_models.py
arcade_clickup/tools/__init__.py
arcade_clickup/tools/comments.py
arcade_clickup/tools/foundation_tools.py
arcade_clickup/tools/system_context.py
arcade_clickup/tools/tasks.py
arcade_clickup/tools/threaded_comments.py
arcade_clickup/tools/fuzzy_search/FUZZY_SEARCH_LOGIC.md
arcade_clickup/tools/fuzzy_search/__init__.py
arcade_clickup/tools/fuzzy_search/search.py
arcade_clickup/utils/__init__.py
arcade_clickup/utils/comment_helpers.py
arcade_clickup/utils/fuzzy_search_helpers.py
arcade_clickup/utils/fuzzy_search_utils.py
arcade_clickup/utils/helpers.py
arcade_clickup/utils/offset_helper.py
arcade_clickup/utils/system_context_helper.py
arcade_clickup/utils/task_filter_helpers.py
arcade_clickup/utils/task_helpers.py
arcade_clickup-1.1.1.dist-info/METADATA
arcade_clickup-1.1.1.dist-info/WHEEL
arcade_clickup-1.1.1.dist-info/licenses/LICENSE
arcade_clickup-1.1.1.dist-info/RECORD
